{
  "slug": "t-124",
  "label": "Jobcenter Knife Attacks",
  "description": "Keywords: Täter, Aschaffenburg, Bielefeld, Magdeburg, Taten, Jobcenter, Jobcenters, verletzt, schrecklichen, Messer",
  "mismatch_score": 0.23138622317464425,
  "norm_delta": 0.23138622317464425,
  "totals": {
    "bundestag_minutes": 89,
    "talkshow_minutes": 1,
    "bt_share": 97.3479475993154,
    "ts_share": 2.6520524006845902,
    "bt_normalized_perc": 0.23786642368775507,
    "ts_normalized_perc": 0.006480200513110817
  },
  "timeseries": []
}