{
  "slug": "t-94",
  "label": "Trust in Democracy",
  "description": "Keywords: Wahlbeteiligung, Misstrauen, durchhaltbar, Vertrauen, Demokraten, Million Dollar, Digitalität, Demokratie, Misstrauen vertrauen, Millionen AfD",
  "mismatch_score": -0.1521544073315588,
  "norm_delta": 0.1521544073315588,
  "totals": {
    "bundestag_minutes": 4,
    "talkshow_minutes": 25,
    "bt_share": 6.644269866632278,
    "ts_share": 93.35573013336771,
    "bt_normalized_perc": 0.011658838873184052,
    "ts_normalized_perc": 0.16381324620474286
  },
  "timeseries": []
}